{
  "kind": "collectionType",
  "collectionName": "bonos",
  "info": {
    "name": "Bonos"
  },
  "options": {
    "increments": true,
    "timestamps": true,
    "draftAndPublish": true
  },
  "pluginOptions": {},
  "attributes": {
    "nombre": {
      "type": "string"
    },
    "valorBono": {
      "type": "biginteger"
    },
    "descuento": {
      "type": "decimal"
    },
    "valorDescuento": {
      "type": "float"
    },
    "bonos": {
      "type": "integer"
    },
    "duracion": {
      "type": "integer"
    },
    "subTotalCosto": {
      "type": "float"
    },
    "BonosCosto": {
      "via": "bono",
      "model": "costo-recursos-humanos"
    }
  }
}
